<annotation>
	<folder></folder>
	<filename>13_i_jpg.rf.7e47a946854723f79f4ec7e2218ca604.jpg</filename>
	<path>13_i_jpg.rf.7e47a946854723f79f4ec7e2218ca604.jpg</path>
	<source>
		<database>roboflow.com</database>
	</source>
	<size>
		<width>640</width>
		<height>640</height>
		<depth>3</depth>
	</size>
	<segmented>0</segmented>
	<object>
		<name>taxi</name>
		<pose>Unspecified</pose>
		<truncated>0</truncated>
		<difficult>0</difficult>
		<occluded>0</occluded>
		<bndbox>
			<xmin>187</xmin>
			<xmax>454</xmax>
			<ymin>138</ymin>
			<ymax>626</ymax>
		</bndbox>
	</object>
</annotation>
