<annotation>
	<folder></folder>
	<filename>2013-Mitsubishi-18ft-Refrigerated-Va_jpg.rf.d36b698b600789f24bd9c5509bf8fd3f.jpg</filename>
	<path>2013-Mitsubishi-18ft-Refrigerated-Va_jpg.rf.d36b698b600789f24bd9c5509bf8fd3f.jpg</path>
	<source>
		<database>roboflow.ai</database>
	</source>
	<size>
		<width>416</width>
		<height>416</height>
		<depth>3</depth>
	</size>
	<segmented>0</segmented>
	<object>
		<name>truck</name>
		<pose>Unspecified</pose>
		<truncated>0</truncated>
		<difficult>0</difficult>
		<occluded>0</occluded>
		<bndbox>
			<xmin>48</xmin>
			<xmax>402</xmax>
			<ymin>24</ymin>
			<ymax>397</ymax>
		</bndbox>
	</object>
</annotation>
