<?xml version="1.0" ?>
<annotation>
  <filename>4289.jpg</filename>
  <size>
    <width>1024</width>
    <height>1024</height>
  </size>
  <object>
    <name>non-vehicle</name>
    <bndbox>
      <xmin>80</xmin>
      <ymin>590</ymin>
      <xmax>435</xmax>
      <ymax>1006</ymax>
    </bndbox>
  </object>
  <object>
    <name>non-vehicle</name>
    <bndbox>
      <xmin>594</xmin>
      <ymin>596</ymin>
      <xmax>930</xmax>
      <ymax>1006</ymax>
    </bndbox>
  </object>
  <object>
    <name>non-vehicle</name>
    <bndbox>
      <xmin>330</xmin>
      <ymin>101</ymin>
      <xmax>853</xmax>
      <ymax>613</ymax>
    </bndbox>
  </object>
</annotation>
