<annotation>
	<folder>Car</folder>
	<filename>car_135.jpg</filename>
	<path>C:\Users\Administrator\Desktop\train\train\Car\car_135.jpg</path>
	<source>
		<database>Unknown</database>
	</source>
	<size>
		<width>750</width>
		<height>562</height>
		<depth>3</depth>
	</size>
	<segmented>0</segmented>
	<object>
		<name>car</name>
		<pose>Unspecified</pose>
		<truncated>0</truncated>
		<difficult>0</difficult>
		<bndbox>
			<xmin>133</xmin>
			<ymin>153</ymin>
			<xmax>663</xmax>
			<ymax>343</ymax>
		</bndbox>
	</object>
</annotation>
