<?xml version="1.0" ?>
<annotation>
  <filename>coco_train_000000266618.jpg</filename>
  <size>
    <width>640</width>
    <height>480</height>
  </size>
  <object>
    <name>non-vehicle</name>
    <bndbox>
      <xmin>299</xmin>
      <ymin>272</ymin>
      <xmax>395</xmax>
      <ymax>443</ymax>
    </bndbox>
  </object>
  <object>
    <name>non-vehicle</name>
    <bndbox>
      <xmin>0</xmin>
      <ymin>214</ymin>
      <xmax>42</xmax>
      <ymax>249</ymax>
    </bndbox>
  </object>
  <object>
    <name>non-vehicle</name>
    <bndbox>
      <xmin>595</xmin>
      <ymin>233</ymin>
      <xmax>639</xmax>
      <ymax>339</ymax>
    </bndbox>
  </object>
</annotation>
