<?xml version="1.0" ?>
<annotation>
  <filename>coco_train_000000448839.jpg</filename>
  <size>
    <width>640</width>
    <height>480</height>
  </size>
  <object>
    <name>non-vehicle</name>
    <bndbox>
      <xmin>401</xmin>
      <ymin>262</ymin>
      <xmax>438</xmax>
      <ymax>431</ymax>
    </bndbox>
  </object>
  <object>
    <name>non-vehicle</name>
    <bndbox>
      <xmin>224</xmin>
      <ymin>239</ymin>
      <xmax>299</xmax>
      <ymax>372</ymax>
    </bndbox>
  </object>
  <object>
    <name>non-vehicle</name>
    <bndbox>
      <xmin>371</xmin>
      <ymin>137</ymin>
      <xmax>396</xmax>
      <ymax>194</ymax>
    </bndbox>
  </object>
  <object>
    <name>non-vehicle</name>
    <bndbox>
      <xmin>341</xmin>
      <ymin>156</ymin>
      <xmax>364</xmax>
      <ymax>238</ymax>
    </bndbox>
  </object>
  <object>
    <name>non-vehicle</name>
    <bndbox>
      <xmin>402</xmin>
      <ymin>96</ymin>
      <xmax>416</xmax>
      <ymax>120</ymax>
    </bndbox>
  </object>
</annotation>
