<?xml version="1.0" ?>
<annotation>
  <filename>coco_train_000000177338.jpg</filename>
  <size>
    <width>640</width>
    <height>427</height>
  </size>
  <object>
    <name>non-vehicle</name>
    <bndbox>
      <xmin>260</xmin>
      <ymin>184</ymin>
      <xmax>482</xmax>
      <ymax>363</ymax>
    </bndbox>
  </object>
  <object>
    <name>non-vehicle</name>
    <bndbox>
      <xmin>364</xmin>
      <ymin>114</ymin>
      <xmax>596</xmax>
      <ymax>317</ymax>
    </bndbox>
  </object>
</annotation>
