<?xml version="1.0" ?>
<annotation>
  <filename>coco_train_000000107183.jpg</filename>
  <size>
    <width>640</width>
    <height>426</height>
  </size>
  <object>
    <name>non-vehicle</name>
    <bndbox>
      <xmin>549</xmin>
      <ymin>318</ymin>
      <xmax>580</xmax>
      <ymax>353</ymax>
    </bndbox>
  </object>
  <object>
    <name>non-vehicle</name>
    <bndbox>
      <xmin>47</xmin>
      <ymin>342</ymin>
      <xmax>112</xmax>
      <ymax>389</ymax>
    </bndbox>
  </object>
</annotation>
