<annotation>
	<folder></folder>
	<filename>Image_013412_jpg.rf.7ece9034478b301bec4793d50e03cc5a.jpg</filename>
	<path>Image_013412_jpg.rf.7ece9034478b301bec4793d50e03cc5a.jpg</path>
	<source>
		<database>roboflow.ai</database>
	</source>
	<size>
		<width>416</width>
		<height>416</height>
		<depth>3</depth>
	</size>
	<segmented>0</segmented>
	<object>
		<name>truck</name>
		<pose>Unspecified</pose>
		<truncated>0</truncated>
		<difficult>0</difficult>
		<occluded>0</occluded>
		<bndbox>
			<xmin>64</xmin>
			<xmax>332</xmax>
			<ymin>60</ymin>
			<ymax>343</ymax>
		</bndbox>
	</object>
</annotation>
