<annotation>
	<folder></folder>
	<filename>maxresdefault-12_jpg.rf.0db52c0ab5f7c881ece3c2427ba37ab8.jpg</filename>
	<path>maxresdefault-12_jpg.rf.0db52c0ab5f7c881ece3c2427ba37ab8.jpg</path>
	<source>
		<database>roboflow.ai</database>
	</source>
	<size>
		<width>416</width>
		<height>416</height>
		<depth>3</depth>
	</size>
	<segmented>0</segmented>
	<object>
		<name>truck</name>
		<pose>Unspecified</pose>
		<truncated>0</truncated>
		<difficult>0</difficult>
		<occluded>0</occluded>
		<bndbox>
			<xmin>3</xmin>
			<xmax>363</xmax>
			<ymin>94</ymin>
			<ymax>416</ymax>
		</bndbox>
	</object>
</annotation>
