<annotation>
	<folder></folder>
	<filename>Modifikasi-Truk-Ragasa_jpg.rf.9a0686820c3d2f86db114e6a0e90e27d.jpg</filename>
	<path>Modifikasi-Truk-Ragasa_jpg.rf.9a0686820c3d2f86db114e6a0e90e27d.jpg</path>
	<source>
		<database>roboflow.ai</database>
	</source>
	<size>
		<width>416</width>
		<height>416</height>
		<depth>3</depth>
	</size>
	<segmented>0</segmented>
	<object>
		<name>truck</name>
		<pose>Unspecified</pose>
		<truncated>0</truncated>
		<difficult>0</difficult>
		<occluded>0</occluded>
		<bndbox>
			<xmin>1</xmin>
			<xmax>416</xmax>
			<ymin>21</ymin>
			<ymax>336</ymax>
		</bndbox>
	</object>
</annotation>
