<?xml version="1.0" ?>
<annotation>
  <filename>Obj365_train_obj365_train_000000286078.jpg</filename>
  <size>
    <width>640</width>
    <height>480</height>
  </size>
  <object>
    <name>non-vehicle</name>
    <bndbox>
      <xmin>597</xmin>
      <ymin>386</ymin>
      <xmax>636</xmax>
      <ymax>458</ymax>
    </bndbox>
  </object>
  <object>
    <name>non-vehicle</name>
    <bndbox>
      <xmin>68</xmin>
      <ymin>347</ymin>
      <xmax>86</xmax>
      <ymax>375</ymax>
    </bndbox>
  </object>
</annotation>
