<?xml version="1.0" ?>
<annotation>
  <filename>Obj365_train_obj365_train_000000241469.jpg</filename>
  <size>
    <width>800</width>
    <height>512</height>
  </size>
  <object>
    <name>non-vehicle</name>
    <bndbox>
      <xmin>47</xmin>
      <ymin>313</ymin>
      <xmax>207</xmax>
      <ymax>411</ymax>
    </bndbox>
  </object>
  <object>
    <name>non-vehicle</name>
    <bndbox>
      <xmin>305</xmin>
      <ymin>340</ymin>
      <xmax>488</xmax>
      <ymax>493</ymax>
    </bndbox>
  </object>
</annotation>
