<annotation>
	<folder></folder>
	<filename>xe-tai-mitsubishi-fuso-canter-12-8-4_jpg.rf.f23d46d99dd1189b2ed1ef0787de0397.jpg</filename>
	<path>xe-tai-mitsubishi-fuso-canter-12-8-4_jpg.rf.f23d46d99dd1189b2ed1ef0787de0397.jpg</path>
	<source>
		<database>roboflow.ai</database>
	</source>
	<size>
		<width>416</width>
		<height>416</height>
		<depth>3</depth>
	</size>
	<segmented>0</segmented>
	<object>
		<name>truck</name>
		<pose>Unspecified</pose>
		<truncated>0</truncated>
		<difficult>0</difficult>
		<occluded>0</occluded>
		<bndbox>
			<xmin>16</xmin>
			<xmax>364</xmax>
			<ymin>17</ymin>
			<ymax>407</ymax>
		</bndbox>
	</object>
</annotation>
